dbnd_snowflake/__init__.py
dbnd_snowflake/sdk/__init__.py
dbnd_snowflake/sdk/snowflake_tracker.py
dbnd_snowflake-1.0.30.1.dist-info/LICENSE
dbnd_snowflake-1.0.30.1.dist-info/METADATA
dbnd_snowflake-1.0.30.1.dist-info/WHEEL
dbnd_snowflake-1.0.30.1.dist-info/top_level.txt
dbnd_snowflake-1.0.30.1.dist-info/RECORD
